gazeru/__init__.py
gazeru/config.py
gazeru/exception.py
gazeru/gazeru.py
gazeru/main.py
gazeru/mp3extractor.py
gazeru/nicovideo_api.py
gazeru/sound_extractor.py
gazeru/tag.py
gazeru-3.1.0.data/scripts/gazeru
gazeru-3.1.0.dist-info/DESCRIPTION.rst
gazeru-3.1.0.dist-info/METADATA
gazeru-3.1.0.dist-info/RECORD
gazeru-3.1.0.dist-info/WHEEL
gazeru-3.1.0.dist-info/metadata.json
gazeru-3.1.0.dist-info/top_level.txt
