Metadata-Version: 2.0
Name: gazeru
Version: 3.1.0
Summary: A crawler for niconico
Home-page: http://github.com/roronya/gazeru
Author: roronya
Author-email: roronya628@gmail.com
License: MIT
Keywords: niconico crawler
Platform: UNKNOWN
Classifier: Development Status :: 5 - Production/Stable
Classifier: Intended Audience :: Developers
Classifier: Topic :: Utilities
Classifier: License :: OSI Approved :: MIT License
Classifier: Programming Language :: Python :: 3
Requires-Dist: beautifulsoup4
Requires-Dist: mutagen
Requires-Dist: nicopy
Requires-Dist: requests
